hatch_datadog_build_metadata/__about__.py
hatch_datadog_build_metadata/__init__.py
hatch_datadog_build_metadata/hooks.py
hatch_datadog_build_metadata/metadata_hook.py
hatch_datadog_build_metadata/vcs_utils.py
hatch_datadog_build_metadata-0.1.0.dist-info/METADATA
hatch_datadog_build_metadata-0.1.0.dist-info/WHEEL
hatch_datadog_build_metadata-0.1.0.dist-info/entry_points.txt
hatch_datadog_build_metadata-0.1.0.dist-info/licenses/LICENSE.txt
hatch_datadog_build_metadata-0.1.0.dist-info/RECORD
