Metadata-Version: 2.1
Name: hatch-datadog-build-metadata
Version: 0.1.0
Summary: Hatch build plugin for source code metadata used by APM
Project-URL: History, https://github.com/DataDog/hatch-datadog-build-metadata/blob/master/HISTORY.md
Project-URL: Issues, https://github.com/DataDog/hatch-datadog-build-metadata/issues
Project-URL: Source, https://github.com/DataDog/hatch-datadog-build-metadata
Author-email: "Datadog, Inc." <dev@datadoghq.com>
License-Expression: MIT
License-File: LICENSE.txt
Keywords: apm,datadog,git,hatch,plugin,tracing
Classifier: Development Status :: 4 - Beta
Classifier: Programming Language :: Python
Classifier: Programming Language :: Python :: 3.7
Classifier: Programming Language :: Python :: 3.8
Classifier: Programming Language :: Python :: 3.9
Classifier: Programming Language :: Python :: 3.10
Classifier: Programming Language :: Python :: 3.11
Classifier: Programming Language :: Python :: Implementation :: CPython
Classifier: Programming Language :: Python :: Implementation :: PyPy
Requires-Python: >=3.7
Requires-Dist: hatchling>=1.1.0
